<?xml version = '1.0' encoding = 'UTF-8'?>
<TableProxyOraclev12c class="oracle.dbtools.crest.model.design.storage.oracle.v12c.TableProxyOraclev12c" name="CUSTOMER" directorySegmentName="seg_0" id="59067129-2414-E66F-FFCD-BC8BA934CCC3">
<createdBy>ntdmi</createdBy>
<createdTime>2025-11-10 06:55:52 UTC</createdTime>
<ownerDesignName>a</ownerDesignName>
<schemaObject>1B01873A-DFF2-C5D2-4E3D-CA3A73BE68B7</schemaObject>
<logging>YES</logging>
<partitionedRowMovement>DISABLE</partitionedRowMovement>
<temporaryChanged>false</temporaryChanged>
<accessDriverType>oracle_loader</accessDriverType>
<rejectLimit></rejectLimit>
<columnProxies itemClass="oracle.dbtools.crest.model.design.storage.oracle.v12c.ColumnProxyOraclev12c">
<ColumnProxy name="CREATED_AT" id="06164476-C4CB-A02F-A25A-D3F677C2B7C9">
<createdBy>ntdmi</createdBy>
<createdTime>2025-11-10 06:55:52 UTC</createdTime>
<ownerDesignName>a</ownerDesignName>
<defaultValue>SYSTIMESTAMP</defaultValue>
</ColumnProxy>
<ColumnProxy name="PUBLIC_KEY" id="11678869-C7A7-4B21-AC80-872FE184180F">
<createdBy>ntdmi</createdBy>
<createdTime>2025-11-10 06:55:52 UTC</createdTime>
<ownerDesignName>a</ownerDesignName>
</ColumnProxy>
<ColumnProxy name="PASSWORD_HASH" id="1D7ABFF4-7F50-417E-F1ED-F6437D0B358F">
<createdBy>ntdmi</createdBy>
<createdTime>2025-11-10 06:55:52 UTC</createdTime>
<ownerDesignName>a</ownerDesignName>
</ColumnProxy>
<ColumnProxy name="FULL_NAME" id="82EC37C3-9D61-43D6-FF73-61DD61A0343B">
<createdBy>ntdmi</createdBy>
<createdTime>2025-11-10 06:55:52 UTC</createdTime>
<ownerDesignName>a</ownerDesignName>
</ColumnProxy>
<ColumnProxy name="PHONE" id="A6B34A24-ED3D-5489-643C-D24C7B30044B">
<createdBy>ntdmi</createdBy>
<createdTime>2025-11-10 06:55:52 UTC</createdTime>
<ownerDesignName>a</ownerDesignName>
</ColumnProxy>
<ColumnProxy name="ADDRESS" id="AAFA93FB-D00C-2622-329E-77A9A8BD36D4">
<createdBy>ntdmi</createdBy>
<createdTime>2025-11-10 06:55:52 UTC</createdTime>
<ownerDesignName>a</ownerDesignName>
</ColumnProxy>
<ColumnProxy name="EMAIL" id="CC2F209C-E16C-29DE-3DAD-7493F58D5DB4">
<createdBy>ntdmi</createdBy>
<createdTime>2025-11-10 06:55:52 UTC</createdTime>
<ownerDesignName>a</ownerDesignName>
</ColumnProxy>
</columnProxies>
<primaryKeys>
<PrimaryKey class="oracle.dbtools.crest.model.design.storage.oracle.v10g.PKProxyOraclev10g" name="CUSTOMER_PK" id="477B8003-BA0C-8804-8E63-F1CE2A9EB47A">
<createdBy>ntdmi</createdBy>
<createdTime>2025-11-10 06:55:52 UTC</createdTime>
<ownerDesignName>a</ownerDesignName>
<schemaObject>1B01873A-DFF2-C5D2-4E3D-CA3A73BE68B7</schemaObject>
<indexSort>SORTED</indexSort>
</PrimaryKey>
</primaryKeys>
</TableProxyOraclev12c>